src/mytcli/__init__.py
src/mytcli/myt.py
tests/test_myt.py
myt_cli-0.1.9.dist-info/LICENSE
myt_cli-0.1.9.dist-info/METADATA
myt_cli-0.1.9.dist-info/WHEEL
myt_cli-0.1.9.dist-info/entry_points.txt
myt_cli-0.1.9.dist-info/top_level.txt
myt_cli-0.1.9.dist-info/RECORD
