Metadata-Version: 2.1
Name: myt-cli
Version: 0.1.9
Summary: myt - My Task Manager
Author-email: Nitin Mathew <nitn_mathew2000@hotmail.com>
Project-URL: Homepage, https://github.com/nsmathew/myt-cli
Project-URL: Issues, https://github.com/nsmathew/myt-cli/issues
Classifier: Development Status :: 5 - Production/Stable
Classifier: Environment :: Console
Classifier: Intended Audience :: Science/Research
Classifier: License :: OSI Approved :: MIT License
Classifier: Programming Language :: Python
Classifier: Operating System :: Microsoft :: Windows
Classifier: Operating System :: MacOS
Classifier: Operating System :: POSIX :: Linux
Classifier: Topic :: Office/Business
Requires-Python: >=3.8
License-File: LICENSE
Requires-Dist: Click
Requires-Dist: rich
Requires-Dist: python-dateutil
Requires-Dist: mock
Requires-Dist: sqlalchemy
